{
  "products": [
    {
      "id": 1,
      "name": "Computer",
      "price": 4300,
      "quantity": 600,
      "selected": true,
      "available": true
    },
    {
      "id": 2,
      "name": "Printer",
      "price": 6990,
      "quantity": 450,
      "selected": false,
      "available": true
    },
    {
      "id": 3,
      "name": "Writer1000",
      "price": 6990,
      "quantity": 450,
      "selected": true,
      "available": false
    },
    {
      "id": 6,
      "name": "Pain",
      "price": 972,
      "quantity": 100,
      "selected": false,
      "available": true
    }
  ]
}